ingress.py
ingress-0.4.1.dist-info/LICENSE.txt
ingress-0.4.1.dist-info/METADATA
ingress-0.4.1.dist-info/WHEEL
ingress-0.4.1.dist-info/top_level.txt
ingress-0.4.1.dist-info/zip-safe
ingress-0.4.1.dist-info/RECORD
